strimilarity.py
strimilarity-1.0.1.dist-info/LICENSE
strimilarity-1.0.1.dist-info/METADATA
strimilarity-1.0.1.dist-info/WHEEL
strimilarity-1.0.1.dist-info/top_level.txt
strimilarity-1.0.1.dist-info/RECORD
